superextensionsfromjupytersprints/__init__.py
superextensionsfromjupytersprints-0.0.1.dist-info/LICENSE
superextensionsfromjupytersprints-0.0.1.dist-info/WHEEL
superextensionsfromjupytersprints-0.0.1.dist-info/METADATA
superextensionsfromjupytersprints-0.0.1.dist-info/RECORD
