Metadata-Version: 1.2
Name: superextensionsfromjupytersprints
Version: 0.0.1
Summary: This is an example package
Home-page: https://github.com/Carreau/superextensionsfromjupytersprints
License: UNKNOWN
Author: Matthias Bussonnier
Author-email: bussonniermatthias@gmail.com
Classifier: License :: OSI Approved :: MIT License
